{"images":[{"startdate":"20230711","fullstartdate":"202307111600","enddate":"20230712","url":"\/th?id=OHR.NakupendaBeach_ZH-CN7913805608_1920x1080.jpg&rf=LaDigue_1920x1080.jpg&pid=hp","urlbase":"\/th?id=OHR.NakupendaBeach_ZH-CN7913805608","copyright":"\u201c\u6211\u7231\u4f60\u201d\u6d77\u6ee9\u81ea\u7136\u4fdd\u62a4\u533a\u7684\u6c99\u6d32\uff0c\u6851\u7ed9\u5df4\u5c14\uff0c\u5766\u6851\u5c3c\u4e9a (\u00a9 Lubos Paukeje\/Alamy)","copyrightlink":"https:\/\/www.bing.com\/search?q=%E5%9D%A6%E6%A1%91%E5%B0%BC%E4%BA%9A%E6%A1%91%E7%BB%99%E5%B7%B4%E5%B0%94&form=hpcapt&mkt=zh-cn","title":"\u4e16\u754c\u4e0a\u6700\u72ec\u7279\u7684\u6d77\u6ee9\uff1f","quiz":"\/search?q=Bing+homepage+quiz&filters=WQOskey:%22HPQuiz_20230711_NakupendaBeach%22&FORM=HPQUIZ","wp":true,"hsh":"11ec21c3913f74b8885cbb989c0aa477","drk":1,"top":1,"bot":1,"hs":[]}],"tooltips":{"loading":"\u6b63\u5728\u52a0\u8f7d...","previous":"\u4e0a\u4e00\u4e2a\u56fe\u50cf","next":"\u4e0b\u4e00\u4e2a\u56fe\u50cf","walle":"\u6b64\u56fe\u7247\u4e0d\u80fd\u4e0b\u8f7d\u7528\u4f5c\u58c1\u7eb8\u3002","walls":"\u4e0b\u8f7d\u4eca\u65e5\u7f8e\u56fe\u3002\u4ec5\u9650\u7528\u4f5c\u684c\u9762\u58c1\u7eb8\u3002"}}