{"images":[{"startdate":"20220715","fullstartdate":"202207151600","enddate":"20220716","url":"\/th?id=OHR.AmericanGoldfinch_ZH-CN2996912015_1920x1080.jpg&rf=LaDigue_1920x1080.jpg&pid=hp","urlbase":"\/th?id=OHR.AmericanGoldfinch_ZH-CN2996912015","copyright":"\u5411\u65e5\u8475\u4e0a\u7684\u91d1\u7fc5\u96c0\uff0c\u7f8e\u56fd\u5357\u5361\u7f57\u6765\u7eb3\u5dde (\u00a9 Teresa Kopec\/Getty Images)","copyrightlink":"https:\/\/www.bing.com\/search?q=%E7%BE%8E%E6%B4%B2%E9%87%91%E7%BF%85%E9%9B%80&form=hpcapt&mkt=zh-cn","title":"\u201c\u85af\u7247\u9e1f\u201d","quiz":"\/search?q=Bing+homepage+quiz&filters=WQOskey:%22HPQuiz_20220715_AmericanGoldfinch%22&FORM=HPQUIZ","wp":true,"hsh":"86cb8649e4e55199fe55376c64093b7a","drk":1,"top":1,"bot":1,"hs":[]}],"tooltips":{"loading":"\u6b63\u5728\u52a0\u8f7d...","previous":"\u4e0a\u4e00\u4e2a\u56fe\u50cf","next":"\u4e0b\u4e00\u4e2a\u56fe\u50cf","walle":"\u6b64\u56fe\u7247\u4e0d\u80fd\u4e0b\u8f7d\u7528\u4f5c\u58c1\u7eb8\u3002","walls":"\u4e0b\u8f7d\u4eca\u65e5\u7f8e\u56fe\u3002\u4ec5\u9650\u7528\u4f5c\u684c\u9762\u58c1\u7eb8\u3002"}}