{"images":[{"startdate":"20220703","fullstartdate":"202207031600","enddate":"20220704","url":"\/th?id=OHR.SharavatiBridge_ZH-CN2011371774_1920x1080.jpg&rf=LaDigue_1920x1080.jpg&pid=hp","urlbase":"\/th?id=OHR.SharavatiBridge_ZH-CN2011371774","copyright":"\u4e00\u5217\u706b\u8f66\u7a7f\u8fc7\u5361\u7eb3\u5854\u514b\u90a6\u7684\u6c99\u62c9\u74e6\u8482\u6865\uff0c\u5370\u5ea6 (\u00a9 Amith Nag Photography\/Getty Images)","copyrightlink":"https:\/\/www.bing.com\/search?q=%E5%8D%A1%E7%BA%B3%E5%A1%94%E5%85%8B%E9%82%A6&form=hpcapt&mkt=zh-cn","title":"\u5de5\u7a0b\u5947\u8ff9","quiz":"\/search?q=Bing+homepage+quiz&filters=WQOskey:%22HPQuiz_20220703_SharavatiBridge%22&FORM=HPQUIZ","wp":true,"hsh":"12ee697dbadb3d7008ee818ea8346f44","drk":1,"top":1,"bot":1,"hs":[]}],"tooltips":{"loading":"\u6b63\u5728\u52a0\u8f7d...","previous":"\u4e0a\u4e00\u4e2a\u56fe\u50cf","next":"\u4e0b\u4e00\u4e2a\u56fe\u50cf","walle":"\u6b64\u56fe\u7247\u4e0d\u80fd\u4e0b\u8f7d\u7528\u4f5c\u58c1\u7eb8\u3002","walls":"\u4e0b\u8f7d\u4eca\u65e5\u7f8e\u56fe\u3002\u4ec5\u9650\u7528\u4f5c\u684c\u9762\u58c1\u7eb8\u3002"}}