{"images":[{"startdate":"20230305","fullstartdate":"202303051600","enddate":"20230306","url":"\/th?id=OHR.IcelandHorses_ZH-CN7213041152_1920x1080.jpg&rf=LaDigue_1920x1080.jpg&pid=hp","urlbase":"\/th?id=OHR.IcelandHorses_ZH-CN7213041152","copyright":"\u7ad9\u5728\u81ea\u5df1\u9886\u57df\u7684\u51b0\u5c9b\u9a6c\uff0c\u51b0\u5c9b (\u00a9 Rodrigo Lourezini\/Shutterstock)","copyrightlink":"https:\/\/www.bing.com\/search?q=%E5%86%B0%E5%B2%9B%E9%A9%AC&form=hpcapt&mkt=zh-cn","title":"\u8fd9\u4e9b\u72ec\u7279\u7684\u751f\u7269\u662f\u4ec0\u4e48?","quiz":"\/search?q=Bing+homepage+quiz&filters=WQOskey:%22HPQuiz_20230305_IcelandHorses%22&FORM=HPQUIZ","wp":true,"hsh":"22cd64abcd3c929d81b08eda41400bdf","drk":1,"top":1,"bot":1,"hs":[]}],"tooltips":{"loading":"\u6b63\u5728\u52a0\u8f7d...","previous":"\u4e0a\u4e00\u4e2a\u56fe\u50cf","next":"\u4e0b\u4e00\u4e2a\u56fe\u50cf","walle":"\u6b64\u56fe\u7247\u4e0d\u80fd\u4e0b\u8f7d\u7528\u4f5c\u58c1\u7eb8\u3002","walls":"\u4e0b\u8f7d\u4eca\u65e5\u7f8e\u56fe\u3002\u4ec5\u9650\u7528\u4f5c\u684c\u9762\u58c1\u7eb8\u3002"}}