{"images":[{"startdate":"20230217","fullstartdate":"202302171600","enddate":"20230218","url":"\/th?id=OHR.EbenIceCave_ZH-CN6035107581_1920x1080.jpg&rf=LaDigue_1920x1080.jpg&pid=hp","urlbase":"\/th?id=OHR.EbenIceCave_ZH-CN6035107581","copyright":"\u57c3\u672c\u51b0\u6d1e\uff0c\u5bc6\u6b47\u6839\u4e0a\u534a\u5c9b\uff0c\u7f8e\u56fd (\u00a9 Dean Pennala\/Shutterstock)","copyrightlink":"https:\/\/www.bing.com\/search?q=%E5%86%B0%E6%B4%9E&form=hpcapt&mkt=zh-cn","title":"\u4ee4\u4eba\u53f9\u4e3a\u89c2\u6b62\u7684\u51b0\u6d1e","quiz":"\/search?q=Bing+homepage+quiz&filters=WQOskey:%22HPQuiz_20230217_EbenIceCave%22&FORM=HPQUIZ","wp":true,"hsh":"a89b1a70fba0b14c2b8ee7af2ce71f56","drk":1,"top":1,"bot":1,"hs":[]}],"tooltips":{"loading":"\u6b63\u5728\u52a0\u8f7d...","previous":"\u4e0a\u4e00\u4e2a\u56fe\u50cf","next":"\u4e0b\u4e00\u4e2a\u56fe\u50cf","walle":"\u6b64\u56fe\u7247\u4e0d\u80fd\u4e0b\u8f7d\u7528\u4f5c\u58c1\u7eb8\u3002","walls":"\u4e0b\u8f7d\u4eca\u65e5\u7f8e\u56fe\u3002\u4ec5\u9650\u7528\u4f5c\u684c\u9762\u58c1\u7eb8\u3002"}}